ost/Project.py
ost/__init__.py
ost/generic/__init__.py
ost/generic/ard_to_ts.py
ost/generic/common_wrappers.py
ost/generic/mosaic.py
ost/generic/timescan.py
ost/generic/ts_extent.py
ost/generic/ts_ls_mask.py
ost/graphs/S1_GRD2ARD/1_AO_TNR.xml
ost/graphs/S1_GRD2ARD/1_AO_TNR_SUB.xml
ost/graphs/S1_GRD2ARD/2_CalBeta_TF.xml
ost/graphs/S1_GRD2ARD/2_CalGamma.xml
ost/graphs/S1_GRD2ARD/2_CalSigma.xml
ost/graphs/S1_GRD2ARD/3_LSmap.xml
ost/graphs/S1_GRD2ARD/3_ML_TC.xml
ost/graphs/S1_GRD2ARD/3_ML_TC_deg.xml
ost/graphs/S1_SLC2ARD/S1_SLC_BurstSplit_AO.xml
ost/graphs/S1_SLC2ARD/S1_SLC_Coh_Deb.xml
ost/graphs/S1_SLC2ARD/S1_SLC_Coreg.xml
ost/graphs/S1_SLC2ARD/S1_SLC_Deb_Halpha.xml
ost/graphs/S1_SLC2ARD/S1_SLC_Deb_Spk_Halpha.xml
ost/graphs/S1_SLC2ARD/S1_SLC_ML_TC.xml
ost/graphs/S1_SLC2ARD/S1_SLC_TNR_CalBeta_Deb_ML_TF_Sub.xml
ost/graphs/S1_SLC2ARD/S1_SLC_TNR_CalGamma_Deb_ML_Sub.xml
ost/graphs/S1_SLC2ARD/S1_SLC_TNR_CalSigma_Deb_ML_Sub.xml
ost/graphs/S1_TS/1_BS_Stacking.xml
ost/graphs/S1_TS/1_BS_Stacking_HAalpha.xml
ost/graphs/S1_TS/1_BS_Stacking_Subset.xml
ost/graphs/ard_json/grd.ceos.json
ost/graphs/ard_json/grd.earth_engine.json
ost/graphs/ard_json/grd.ost_gtc.json
ost/graphs/ard_json/grd.ost_rtc.json
ost/graphs/ard_json/slc.ost_gtc.json
ost/graphs/ard_json/slc.ost_minimal.json
ost/graphs/ard_json/slc.ost_rtc.json
ost/helpers/__init__.py
ost/helpers/asf.py
ost/helpers/asf_wget.py
ost/helpers/db.py
ost/helpers/errors.py
ost/helpers/helpers.py
ost/helpers/onda.py
ost/helpers/peps.py
ost/helpers/raster.py
ost/helpers/scihub.py
ost/helpers/settings.py
ost/helpers/srtm.py
ost/helpers/vector.py
ost/s1/__init__.py
ost/s1/burst_batch.py
ost/s1/burst_inventory.py
ost/s1/burst_to_ard.py
ost/s1/download.py
ost/s1/grd_batch.py
ost/s1/grd_to_ard.py
ost/s1/grd_wrappers.py
ost/s1/refine_inventory.py
ost/s1/s1scene.py
ost/s1/search.py
ost/s1/slc_wrappers.py
ost/s1/ts.py
opensartoolkit-0.12.15.dist-info/AUTHORS.rst
opensartoolkit-0.12.15.dist-info/LICENSE
opensartoolkit-0.12.15.dist-info/METADATA
opensartoolkit-0.12.15.dist-info/WHEEL
opensartoolkit-0.12.15.dist-info/top_level.txt
opensartoolkit-0.12.15.dist-info/RECORD
