Metadata-Version: 2.1
Name: opensartoolkit
Version: 0.12.15
Summary: High-level functionality for the inventory, download and pre-processing of Sentinel-1 data
Home-page: https://github.com/ESA-PhiLab/OpenSarToolkit
Author: Andreas Vollrath
Author-email: opensarkit@gmail.com
License: MIT License
Download-URL: https://github.com/ESA-PhiLab/OpenSarToolkit/archive/0.12.15.tar.gz
Keywords: Sentinel-1,ESA,SAR,Radar,Earth Observation,Remote Sensing,Synthetic Aperture Radar
Platform: UNKNOWN
Classifier: Development Status :: 5 - Production/Stable
Classifier: Intended Audience :: Science/Research
Classifier: License :: OSI Approved :: MIT License
Classifier: Natural Language :: English
Classifier: Programming Language :: Python :: 3.7
Classifier: Programming Language :: Python :: 3.8
Classifier: Topic :: Scientific/Engineering :: GIS
Requires-Dist: pyproj
Requires-Dist: descartes
Requires-Dist: godale
Requires-Dist: geopandas (>=0.8)
Requires-Dist: jupyterlab
Requires-Dist: psycopg2-binary
Requires-Dist: rasterio
Requires-Dist: requests
Requires-Dist: scipy
Requires-Dist: tqdm
Requires-Dist: imageio
Requires-Dist: rtree
Requires-Dist: retrying
Provides-Extra: dev
Requires-Dist: pre-commit ; extra == 'dev'
Requires-Dist: pytest ; extra == 'dev'
Requires-Dist: coverage ; extra == 'dev'
Requires-Dist: nbsphinx ; extra == 'dev'
Requires-Dist: pydata-sphinx-theme ; extra == 'dev'
Requires-Dist: sphinx-copybutton ; extra == 'dev'
Requires-Dist: Commitizen ; extra == 'dev'
